{
    "category" : [
                  {
                  "name" : "Cameras",
                  "items" : [
                             {
                             "id" : "1",
                             "name" : "Nikon Coolpix L29 16.1MP Digital Camera",
                             "price" : "$ 381",
                             "location" : "1LC4"
                             },
                             {
                             "id" : "2",
                             "name" : "Nikon Coolpix L30 20 MP Digital Camera",
                             "price" : "$ 490",
                             "location" : "2LC4"
                             },
                             {
                             "id" : "3",
                             "name" : "Nikon Coolpix S2800 20.1MP Digital Camera",
                             "price" : "$ 499",
                             "location" : "3LC4"
                             },
                             {
                             "id" : "4",
                             "name" : "Canon IXUS145 16MP Digital Camera",
                             "price" : "$ 53",
                             "location" : "3LC4"
                             },
                             {
                             "id" : "2",
                             "name" : "Nikon Coolpix L30 20 MP Digital Camera",
                             "price" : "$ 490",
                             "location" : "3LC4"
                             },
                             {
                             "id" : "3",
                             "name" : "Nikon Coolpix S2800 20.1MP Digital Camera",
                             "price" : "$ 499",
                             "location" : "3LC4"
                             },
                             {
                             "id" : "4",
                             "name" : "Canon IXUS145 16MP Digital Camera",
                             "price" : "$ 53",
                             "location" : "3LC4"
                             },
                             {
                             "id" : "2",
                             "name" : "Nikon Coolpix L30 20 MP Digital Camera",
                             "price" : "$ 490",
                             "location" : "3LC4"
                             },
                             {
                             "id" : "3",
                             "name" : "Nikon Coolpix S2800 20.1MP Digital Camera",
                             "price" : "$ 499",
                             "location" : "3LC4"
                             },
                             {
                             "id" : "4",
                             "name" : "Canon IXUS145 16MP Digital Camera",
                             "price" : "$ 53",
                             "location" : "3LC4"
                             }
                             ]
                  },
                  {
                  "name" : "First aid",
                  "items" : [
                             {
                             "id" : "5",
                             "name" : "Coghlan's Trekk Iii First Aid Kit",
                             "price" : "$ 16",
                             "location" : "3LC4"
                             },
                             {
                             "id" : "6",
                             "name" : "Clickforsign First Aid Box Sign Glow In The Dark",
                             "price" : "$ 33",
                             "location" : "3LC4"
                             },
                             {
                             "id" : "7",
                             "name" : "Wild Eye First Aid Stainless Steel 207 ml Hip Flask",
                             "price" : "$ 89",
                             "location" : "3LC4"
                             },
                             {
                             "id" : "8",
                             "name" : "SJB Dr.dolly Doll first aid kit",
                             "price" : "$ 8",
                             "location" : "3LC4"
                             }
                             ]
                  },
                  {
                  "name" : "Eatable",
                  "items" : [
                             {
                             "id" : "9",
                             "name" : "Snapgalaxy Premium Chocolates Tokri & Diwali Wishes Mug",
                             "price" : "$ 10",
                             "location" : "3LC4"
                             },
                             {
                             "id" : "10",
                             "name" : "Snapgalaxy Fine Chocolate Box & Diwali Wishes Mug",
                             "price" : "$ 30",
                             "location" : "3LC4"
                             }
                             ]
                  },
                  {
                  "name" : "Kitchen",
                  "items" : [
                             {
                             "id" : "1",
                             "name" : "Nikon Coolpix L29 16.1MP Digital Camera",
                             "price" : "$ 382",
                             "location" : "3LC4"
                             },
                             {
                             "id" : "2",
                             "name" : "Nikon Coolpix L30 20 MP Digital Camera",
                             "price" : "$ 490",
                             "location" : "3LC4"
                             },
                             {
                             "id" : "3",
                             "name" : "Nikon Coolpix S2800 20.1MP Digital Camera",
                             "price" : "$ 449",
                             "location" : "3LC4"
                             },
                             {
                             "id" : "4",
                             "name" : "Canon IXUS145 16MP Digital Camera",
                             "price" : "$ 513",
                             "location" : "3LC4"
                             }
                             ]
                  },
                  {
                  "name" : "Laptops",
                  "items" : [
                             {
                             "id" : "1",
                             "name" : "Nikon Coolpix L29 16.1MP Digital Camera",
                             "price" : "$ 312",
                             "location" : "3LC4"
                             },
                             {
                             "id" : "2",
                             "name" : "Nikon Coolpix L30 20 MP Digital Camera",
                             "price" : "$ 49",
                             "location" : "3LC4"
                             },
                             {
                             "id" : "3",
                             "name" : "Nikon Coolpix S2800 20.1MP Digital Camera",
                             "price" : "$ 95",
                             "location" : "3LC4"
                             },
                             {
                             "id" : "4",
                             "name" : "Canon IXUS145 16MP Digital Camera",
                             "price" : "$ 58",
                             "location" : "3LC4"
                             }
                             ]
                  },
                  {
                  "name" : "Life style",
                  "items" : [
                             {
                             "id" : "1",
                             "name" : "Nikon Coolpix L29 16.1MP Digital Camera",
                             "price" : "$ 13",
                             "location" : "3LC4"
                             },
                             {
                             "id" : "2",
                             "name" : "Nikon Coolpix L30 20 MP Digital Camera",
                             "price" : "$ 54",
                             "location" : "3LC4"
                             },
                             {
                             "id" : "3",
                             "name" : "Nikon Coolpix S2800 20.1MP Digital Camera",
                             "price" : "$ 45",
                             "location" : "3LC4"
                             },
                             {
                             "id" : "4",
                             "name" : "Canon IXUS145 16MP Digital Camera",
                             "price" : "$ 13",
                             "location" : "3LC4"
                             }
                             ]
                  },
                  {
                  "name" : "Mobiles",
                  "items" : [
                             {
                             "id" : "1",
                             "name" : "Nikon Coolpix L29 16.1MP Digital Camera",
                             "price" : "$ 32",
                             "location" : "3LC4"
                             },
                             {
                             "id" : "2",
                             "name" : "Nikon Coolpix L30 20 MP Digital Camera",
                             "price" : "$ 40",
                             "location" : "3LC4"
                             },
                             {
                             "id" : "3",
                             "name" : "Nikon Coolpix S2800 20.1MP Digital Camera",
                             "price" : "$ 49",
                             "location" : "3LC4"
                             },
                             {
                             "id" : "4",
                             "name" : "Canon IXUS145 16MP Digital Camera",
                             "price" : "$ 513",
                             "location" : "3LC4"
                             }
                             ]
                  },
                  {
                  "name" : "Toys",
                  "items" : [
                             {
                             "id" : "1",
                             "name" : "Nikon Coolpix L29 16.1MP Digital Camera",
                             "price" : "$ 12",
                             "location" : "3LC4"
                             },
                             {
                             "id" : "2",
                             "name" : "Nikon Coolpix L30 20 MP Digital Camera",
                             "price" : "$ 50",
                             "location" : "3LC4"
                             },
                             {
                             "id" : "3",
                             "name" : "Nikon Coolpix S2800 20.1MP Digital Camera",
                             "price" : "$ 49",
                             "location" : "3LC4"
                             },
                             {
                             "id" : "4",
                             "name" : "Canon IXUS145 16MP Digital Camera",
                             "price" : "$ 313",
                             "location" : "3LC4"
                             }
                             ]
                  }
                  ]
}